README.md
setup.py
pyfastq_reader/__init__.py
pyfastq_reader.egg-info/PKG-INFO
pyfastq_reader.egg-info/SOURCES.txt
pyfastq_reader.egg-info/dependency_links.txt
pyfastq_reader.egg-info/entry_points.txt
pyfastq_reader.egg-info/top_level.txt